suraj_ka_package/__init__.py
suraj_ka_package/cmain.py
suraj_ka_package/main.py
suraj_ka_package-0.0.6.dist-info/METADATA
suraj_ka_package-0.0.6.dist-info/WHEEL
suraj_ka_package-0.0.6.dist-info/top_level.txt
suraj_ka_package-0.0.6.dist-info/RECORD
