Metadata-Version: 2.1
Name: suraj-ka-package
Version: 0.0.6
Summary: Simple Python function
Author: Suraj Yadav
Author-email: sam124.sy@gmail.com
Classifier: Programming Language :: Python :: 3
Classifier: Operating System :: OS Independent
Requires-Python: >=3.5
